vb_admin/__init__.py
vb_admin/command.py
vb_admin/layout/.bandit
vb_admin/layout/.flake8
vb_admin/layout/.gitignore
vb_admin/layout/.isort.cfg
vb_admin/layout/.pylintrc
vb_admin/layout/Procfile
vb_admin/layout/Rakefile
vb_admin/layout/manage.py
vb_admin/layout/pyproject.toml
vb_admin/layout/requirements.txt
vb_admin/layout/runtime.txt
vb_admin/layout/applications/.gitkeep
vb_admin/layout/config/__init__.py
vb_admin/layout/config/urls.py
vb_admin/layout/config/wsgi.py
vb_admin/layout/config/settings/__init__.py
vb_admin/layout/config/settings/base.py
vb_admin/layout/config/settings/development.example.py
vb_admin/layout/config/settings/heroku.py
vb_admin/layout/config/settings/production.py
vb_admin/layout/config/settings/test.example.py
vb_admin/layout/locale/tr/LC_MESSAGES/django.mo
vb_admin/layout/locale/tr/LC_MESSAGES/django.po
vb_admin/layout/requirements/base.pip
vb_admin/layout/requirements/development.pip
vb_admin/layout/requirements/heroku.pip
vb_admin/layout/requirements/production.pip
vb_admin/layout/static/css/application.css
vb_admin/layout/static/css/bulma.min.0.8.0.css
vb_admin/layout/static/images/.gitkeep
vb_admin/layout/static/js/.gitkeep
vb_admin/layout/static/js/application.js
vb_admin/layout/static/js/fontawesome.5.3.1.all.js
vb_admin/layout/templates/base.html
vb_admin/layout/templates/admin/base_site.html
vb_admin/layout/templates/custom_errors/400.html
vb_admin/layout/templates/custom_errors/403.html
vb_admin/layout/templates/custom_errors/404.html
vb_admin/layout/templates/custom_errors/500.html
django_vb_admin-1.1.10.dist-info/LICENCE
django_vb_admin-1.1.10.dist-info/METADATA
django_vb_admin-1.1.10.dist-info/WHEEL
django_vb_admin-1.1.10.dist-info/entry_points.txt
django_vb_admin-1.1.10.dist-info/top_level.txt
django_vb_admin-1.1.10.dist-info/RECORD
