Metadata-Version: 2.1
Name: django-vb-admin
Version: 1.1.10
Summary: Create custom Django project with style...
Home-page: https://github.com/vbyazilim/django-vb-admin
Author: vb YAZILIM
Author-email: hello@vbyazilim.com
License: MIT
Platform: UNKNOWN
Classifier: License :: OSI Approved :: MIT License
Classifier: Operating System :: OS Independent
Classifier: Development Status :: 5 - Production/Stable
Classifier: Environment :: Console
Classifier: Programming Language :: Python :: 3.6
Classifier: Programming Language :: Python :: 3 :: Only
Classifier: Topic :: Utilities
Classifier: Framework :: Django
Classifier: Topic :: Software Development :: Libraries :: Python Modules
Requires-Python: >=3.6
Requires-Dist: django-vb-baseapp
